setup.py
sphinxmapxrefrole/__init__.py
sphinxmapxrefrole.egg-info/PKG-INFO
sphinxmapxrefrole.egg-info/SOURCES.txt
sphinxmapxrefrole.egg-info/dependency_links.txt
sphinxmapxrefrole.egg-info/pbr.json
sphinxmapxrefrole.egg-info/top_level.txt