Metadata-Version: 1.0
Name: sphinxmapxrefrole
Version: 0.2.2
Summary: Sphinx mapping role
Home-page: http://www.github.com/menpo/sphinx-map-xrefrole
Author: Patrick Snape
Author-email: patricksnape@gmail.com
License: UNKNOWN
Platform: UNKNOWN
